LICENSE
MANIFEST.in
README.md
setup.py
AirtestWithPrefDog/MakePrefData.py
AirtestWithPrefDog/__init__.py
AirtestWithPrefDog/__version__.py
AirtestWithPrefDog/airRunner.py
AirtestWithPrefDog/logAnalysis.py
AirtestWithPrefDog/perfdog_pb2.py
AirtestWithPrefDog/perfdog_pb2_grpc.py
AirtestWithPrefDog/startService.py
AirtestWithPrefDog.egg-info/PKG-INFO
AirtestWithPrefDog.egg-info/SOURCES.txt
AirtestWithPrefDog.egg-info/dependency_links.txt
AirtestWithPrefDog.egg-info/requires.txt
AirtestWithPrefDog.egg-info/top_level.txt