Metadata-Version: 2.1
Name: AirtestWithPrefDog
Version: 0.3.10
Summary: AirtestAndPrefDog Runner.
Home-page: https://github.com/ChenYangRu/AirtestWithPrefDog
Author: ChenYang
Author-email: 466321249@qq.com
License: MIT
Platform: UNKNOWN
Classifier: License :: OSI Approved :: MIT License
Classifier: Programming Language :: Python
Classifier: Programming Language :: Python :: 3
Classifier: Programming Language :: Python :: 3.6
Classifier: Programming Language :: Python :: Implementation :: CPython
Classifier: Programming Language :: Python :: Implementation :: PyPy
Requires-Python: <3.7.0
